for_lossless_music/__init__.py
for_lossless_music/__main__.py
for_lossless_music/api.py
for_lossless_music/download.py
for_lossless_music/moresound.py
for_lossless_music/progressbar.py
for_lossless_music/qqmusic.py
for_lossless_music/quality.py
for_lossless_music/song.py
for_lossless_music/source.py
for_lossless_music-0.1.3.dist-info/LICENSE
for_lossless_music-0.1.3.dist-info/METADATA
for_lossless_music-0.1.3.dist-info/WHEEL
for_lossless_music-0.1.3.dist-info/entry_points.txt
for_lossless_music-0.1.3.dist-info/top_level.txt
for_lossless_music-0.1.3.dist-info/RECORD
