Metadata-Version: 2.1
Name: for-lossless-music
Version: 0.1.3
Summary: For lossless music!
Home-page: https://github.com/comwrg/for-lossless-music
Author: comwrg
Author-email: xcomwrg@gmail.com
License: MIT
Platform: UNKNOWN
Classifier: Programming Language :: Python
Classifier: Programming Language :: Python :: 3.6
Classifier: Programming Language :: Python :: Implementation :: CPython
Classifier: Topic :: Utilities
Classifier: Topic :: Internet :: WWW/HTTP
Classifier: License :: OSI Approved :: MIT License
Requires-Dist: requests
Requires-Dist: prettytable
